testers/__init__.py
testers/api_helper.py
testers/configuration.py
testers/testers_client.py
testers/controllers/__init__.py
testers/controllers/base_controller.py
testers/controllers/body_params_controller.py
testers/controllers/echo_controller.py
testers/controllers/error_codes_controller.py
testers/controllers/form_params_controller.py
testers/controllers/header_controller.py
testers/controllers/query_param_controller.py
testers/controllers/response_types_controller.py
testers/controllers/template_params_controller.py
testers/exceptions/__init__.py
testers/exceptions/api_exception.py
testers/exceptions/global_test_exception.py
testers/exceptions/local_test_exception.py
testers/exceptions/nested_model_exception.py
testers/http/__init__.py
testers/http/http_call_back.py
testers/http/http_method_enum.py
testers/http/http_request.py
testers/http/http_response.py
testers/models/__init__.py
testers/models/attributes.py
testers/models/days.py
testers/models/delete_body.py
testers/models/echo_response.py
testers/models/mtype.py
testers/models/param_format.py
testers/models/person.py
testers/models/query_parameter.py
testers/models/response_with_enum.py
testers/models/server_response.py
testers/models/suite_code.py
testers/models/validate.py
testers/utilities/__init__.py
testers/utilities/file_wrapper.py
tester_stripped_mhr-0.0.1.dist-info/LICENSE
tester_stripped_mhr-0.0.1.dist-info/METADATA
tester_stripped_mhr-0.0.1.dist-info/WHEEL
tester_stripped_mhr-0.0.1.dist-info/top_level.txt
tester_stripped_mhr-0.0.1.dist-info/RECORD
